fe507/__init__.py
fe507/fe507.py
fe507/report.py
fe507/settings.py
fe507/data/BIST100.csv
fe507/data/BISTALL.csv
fe507/data/BTCETH.csv
fe507/data/EXCHANGE.csv
fe507/data/Gold.csv
fe507/data/SP500.csv
fe507/data/TLDEPO.csv
fe507/data/TLINF.csv
fe507/data/data.csv
fe507/data/data.png
fe507/data/index.txt
fe507/data/xlsx/BIST100.xlsx
fe507/data/xlsx/BISTALL.xlsx
fe507/data/xlsx/BTCETH.xlsx
fe507/data/xlsx/DATA FE 2022.xlsx
fe507/data/xlsx/EXCHANGE.xlsx
fe507/data/xlsx/Gold.xlsx
fe507/data/xlsx/SP500.xlsx
fe507/data/xlsx/TLDEPO.xlsx
fe507/data/xlsx/TLINF.xlsx
fe507/data/xlsx/data.numbers
fe507-0.1.12.dist-info/WHEEL
fe507-0.1.12.dist-info/METADATA
fe507-0.1.12.dist-info/RECORD
