Metadata-Version: 2.1
Name: fe507
Version: 0.1.12
Summary: FE507 is a simple yet very powerful, 'batteries included' intuitive package for data analysing.
Author-email: Azat Y <steels-06.gasbag@icloud.com>
Project-URL: Home, https://azat.cc
